my_packages/__init__.py
my_packages/getMax.py
my_packages/getMin.py
my_minmax-1.1.dist-info/LICENSE.txt
my_minmax-1.1.dist-info/METADATA
my_minmax-1.1.dist-info/WHEEL
my_minmax-1.1.dist-info/top_level.txt
my_minmax-1.1.dist-info/RECORD
