Metadata-Version: 2.1
Name: my-minmax
Version: 1.1
Summary: edited by myself
Author: lius
License-File: LICENSE.txt
